core/__init__.py
core/ai.py
core/corrector.py
core/talk.py
core/voice.py
utils/__init__.py
utils/formatter.py
ghost_cli-1.2.dist-info/METADATA
ghost_cli-1.2.dist-info/WHEEL
ghost_cli-1.2.dist-info/entry_points.txt
ghost_cli-1.2.dist-info/top_level.txt
ghost_cli-1.2.dist-info/RECORD
