Metadata-Version: 2.4
Name: ghost_cli
Version: 1.2
Summary: Ghost CLI — AI-powered Smart Corrector and Talk Assistant
Author: Souparno Goswami
Classifier: Programming Language :: Python :: 3
Classifier: Operating System :: OS Independent
Classifier: Intended Audience :: Developers
Classifier: Topic :: Utilities
Classifier: Topic :: Software Development :: Libraries
Requires-Python: >=3.8
Requires-Dist: pyfiglet
Requires-Dist: colorama
Requires-Dist: python-dotenv
Requires-Dist: google-genai
Requires-Dist: pyttsx3
Requires-Dist: pyreadline3
Dynamic: author
Dynamic: classifier
Dynamic: description-content-type
Dynamic: requires-dist
Dynamic: requires-python
Dynamic: summary
